tweego.py
tweego-1.1.0.dist-info/LICENSE
tweego-1.1.0.dist-info/METADATA
tweego-1.1.0.dist-info/WHEEL
tweego-1.1.0.dist-info/entry_points.txt
tweego-1.1.0.dist-info/top_level.txt
tweego-1.1.0.dist-info/RECORD
