Metadata-Version: 2.1
Name: tweego
Version: 1.1.0
Summary: Generate ego networks for users from Twitter.
Home-page: https://github.com/Aveek-Saha/tweego
Author: Aveek Saha
Author-email: aveek.s98@gmail.com
License: UNKNOWN
Platform: UNKNOWN
License-File: LICENSE
Requires-Dist: Click
Requires-Dist: networkx
Requires-Dist: TwitterAPI
Requires-Dist: tqdm
